{
  "warnings": [
    {
      "file": "/Users/Arthur/Documents/oss/siren/Sources/Siren.swift",
      "line": 514,
      "symbol": "Siren.LanguageType.Arabic",
      "symbol_kind": "source.lang.swift.decl.enumelement",
      "warning": "undocumented"
    },
    {
      "file": "/Users/Arthur/Documents/oss/siren/Sources/Siren.swift",
      "line": 515,
      "symbol": "Siren.LanguageType.Armenian",
      "symbol_kind": "source.lang.swift.decl.enumelement",
      "warning": "undocumented"
    },
    {
      "file": "/Users/Arthur/Documents/oss/siren/Sources/Siren.swift",
      "line": 516,
      "symbol": "Siren.LanguageType.Basque",
      "symbol_kind": "source.lang.swift.decl.enumelement",
      "warning": "undocumented"
    },
    {
      "file": "/Users/Arthur/Documents/oss/siren/Sources/Siren.swift",
      "line": 517,
      "symbol": "Siren.LanguageType.ChineseSimplified",
      "symbol_kind": "source.lang.swift.decl.enumelement",
      "warning": "undocumented"
    },
    {
      "file": "/Users/Arthur/Documents/oss/siren/Sources/Siren.swift",
      "line": 518,
      "symbol": "Siren.LanguageType.ChineseTraditional",
      "symbol_kind": "source.lang.swift.decl.enumelement",
      "warning": "undocumented"
    },
    {
      "file": "/Users/Arthur/Documents/oss/siren/Sources/Siren.swift",
      "line": 519,
      "symbol": "Siren.LanguageType.Croatian",
      "symbol_kind": "source.lang.swift.decl.enumelement",
      "warning": "undocumented"
    },
    {
      "file": "/Users/Arthur/Documents/oss/siren/Sources/Siren.swift",
      "line": 520,
      "symbol": "Siren.LanguageType.Danish",
      "symbol_kind": "source.lang.swift.decl.enumelement",
      "warning": "undocumented"
    },
    {
      "file": "/Users/Arthur/Documents/oss/siren/Sources/Siren.swift",
      "line": 521,
      "symbol": "Siren.LanguageType.Dutch",
      "symbol_kind": "source.lang.swift.decl.enumelement",
      "warning": "undocumented"
    },
    {
      "file": "/Users/Arthur/Documents/oss/siren/Sources/Siren.swift",
      "line": 522,
      "symbol": "Siren.LanguageType.English",
      "symbol_kind": "source.lang.swift.decl.enumelement",
      "warning": "undocumented"
    },
    {
      "file": "/Users/Arthur/Documents/oss/siren/Sources/Siren.swift",
      "line": 523,
      "symbol": "Siren.LanguageType.Estonian",
      "symbol_kind": "source.lang.swift.decl.enumelement",
      "warning": "undocumented"
    },
    {
      "file": "/Users/Arthur/Documents/oss/siren/Sources/Siren.swift",
      "line": 524,
      "symbol": "Siren.LanguageType.Finnish",
      "symbol_kind": "source.lang.swift.decl.enumelement",
      "warning": "undocumented"
    },
    {
      "file": "/Users/Arthur/Documents/oss/siren/Sources/Siren.swift",
      "line": 525,
      "symbol": "Siren.LanguageType.French",
      "symbol_kind": "source.lang.swift.decl.enumelement",
      "warning": "undocumented"
    },
    {
      "file": "/Users/Arthur/Documents/oss/siren/Sources/Siren.swift",
      "line": 526,
      "symbol": "Siren.LanguageType.German",
      "symbol_kind": "source.lang.swift.decl.enumelement",
      "warning": "undocumented"
    },
    {
      "file": "/Users/Arthur/Documents/oss/siren/Sources/Siren.swift",
      "line": 527,
      "symbol": "Siren.LanguageType.Greek",
      "symbol_kind": "source.lang.swift.decl.enumelement",
      "warning": "undocumented"
    },
    {
      "file": "/Users/Arthur/Documents/oss/siren/Sources/Siren.swift",
      "line": 528,
      "symbol": "Siren.LanguageType.Hebrew",
      "symbol_kind": "source.lang.swift.decl.enumelement",
      "warning": "undocumented"
    },
    {
      "file": "/Users/Arthur/Documents/oss/siren/Sources/Siren.swift",
      "line": 529,
      "symbol": "Siren.LanguageType.Hungarian",
      "symbol_kind": "source.lang.swift.decl.enumelement",
      "warning": "undocumented"
    },
    {
      "file": "/Users/Arthur/Documents/oss/siren/Sources/Siren.swift",
      "line": 530,
      "symbol": "Siren.LanguageType.Indonesian",
      "symbol_kind": "source.lang.swift.decl.enumelement",
      "warning": "undocumented"
    },
    {
      "file": "/Users/Arthur/Documents/oss/siren/Sources/Siren.swift",
      "line": 531,
      "symbol": "Siren.LanguageType.Italian",
      "symbol_kind": "source.lang.swift.decl.enumelement",
      "warning": "undocumented"
    },
    {
      "file": "/Users/Arthur/Documents/oss/siren/Sources/Siren.swift",
      "line": 532,
      "symbol": "Siren.LanguageType.Japanese",
      "symbol_kind": "source.lang.swift.decl.enumelement",
      "warning": "undocumented"
    },
    {
      "file": "/Users/Arthur/Documents/oss/siren/Sources/Siren.swift",
      "line": 533,
      "symbol": "Siren.LanguageType.Korean",
      "symbol_kind": "source.lang.swift.decl.enumelement",
      "warning": "undocumented"
    },
    {
      "file": "/Users/Arthur/Documents/oss/siren/Sources/Siren.swift",
      "line": 534,
      "symbol": "Siren.LanguageType.Latvian",
      "symbol_kind": "source.lang.swift.decl.enumelement",
      "warning": "undocumented"
    },
    {
      "file": "/Users/Arthur/Documents/oss/siren/Sources/Siren.swift",
      "line": 535,
      "symbol": "Siren.LanguageType.Lithuanian",
      "symbol_kind": "source.lang.swift.decl.enumelement",
      "warning": "undocumented"
    },
    {
      "file": "/Users/Arthur/Documents/oss/siren/Sources/Siren.swift",
      "line": 536,
      "symbol": "Siren.LanguageType.Malay",
      "symbol_kind": "source.lang.swift.decl.enumelement",
      "warning": "undocumented"
    },
    {
      "file": "/Users/Arthur/Documents/oss/siren/Sources/Siren.swift",
      "line": 537,
      "symbol": "Siren.LanguageType.Norwegian",
      "symbol_kind": "source.lang.swift.decl.enumelement",
      "warning": "undocumented"
    },
    {
      "file": "/Users/Arthur/Documents/oss/siren/Sources/Siren.swift",
      "line": 538,
      "symbol": "Siren.LanguageType.Polish",
      "symbol_kind": "source.lang.swift.decl.enumelement",
      "warning": "undocumented"
    },
    {
      "file": "/Users/Arthur/Documents/oss/siren/Sources/Siren.swift",
      "line": 539,
      "symbol": "Siren.LanguageType.PortugueseBrazil",
      "symbol_kind": "source.lang.swift.decl.enumelement",
      "warning": "undocumented"
    },
    {
      "file": "/Users/Arthur/Documents/oss/siren/Sources/Siren.swift",
      "line": 540,
      "symbol": "Siren.LanguageType.PortuguesePortugal",
      "symbol_kind": "source.lang.swift.decl.enumelement",
      "warning": "undocumented"
    },
    {
      "file": "/Users/Arthur/Documents/oss/siren/Sources/Siren.swift",
      "line": 541,
      "symbol": "Siren.LanguageType.Russian",
      "symbol_kind": "source.lang.swift.decl.enumelement",
      "warning": "undocumented"
    },
    {
      "file": "/Users/Arthur/Documents/oss/siren/Sources/Siren.swift",
      "line": 542,
      "symbol": "Siren.LanguageType.SerbianCyrillic",
      "symbol_kind": "source.lang.swift.decl.enumelement",
      "warning": "undocumented"
    },
    {
      "file": "/Users/Arthur/Documents/oss/siren/Sources/Siren.swift",
      "line": 543,
      "symbol": "Siren.LanguageType.SerbianLatin",
      "symbol_kind": "source.lang.swift.decl.enumelement",
      "warning": "undocumented"
    },
    {
      "file": "/Users/Arthur/Documents/oss/siren/Sources/Siren.swift",
      "line": 544,
      "symbol": "Siren.LanguageType.Slovenian",
      "symbol_kind": "source.lang.swift.decl.enumelement",
      "warning": "undocumented"
    },
    {
      "file": "/Users/Arthur/Documents/oss/siren/Sources/Siren.swift",
      "line": 545,
      "symbol": "Siren.LanguageType.Spanish",
      "symbol_kind": "source.lang.swift.decl.enumelement",
      "warning": "undocumented"
    },
    {
      "file": "/Users/Arthur/Documents/oss/siren/Sources/Siren.swift",
      "line": 546,
      "symbol": "Siren.LanguageType.Swedish",
      "symbol_kind": "source.lang.swift.decl.enumelement",
      "warning": "undocumented"
    },
    {
      "file": "/Users/Arthur/Documents/oss/siren/Sources/Siren.swift",
      "line": 547,
      "symbol": "Siren.LanguageType.Thai",
      "symbol_kind": "source.lang.swift.decl.enumelement",
      "warning": "undocumented"
    },
    {
      "file": "/Users/Arthur/Documents/oss/siren/Sources/Siren.swift",
      "line": 548,
      "symbol": "Siren.LanguageType.Turkish",
      "symbol_kind": "source.lang.swift.decl.enumelement",
      "warning": "undocumented"
    },
    {
      "file": "/Users/Arthur/Documents/oss/siren/Sources/Siren.swift",
      "line": 549,
      "symbol": "Siren.LanguageType.Vietnamese",
      "symbol_kind": "source.lang.swift.decl.enumelement",
      "warning": "undocumented"
    }
  ],
  "source_directory": "/Users/Arthur/Documents/oss/siren"
}